[
null,
{"id":1,"animationId":-1,"damage":{"critical":true,"elementId":-1,"formula":"a.atk * (4 + a.level/4) - b.def * 2","type":1,"variance":20},"description":"","effects":[{"code":21,"dataId":0,"value1":1,"value2":0}],"hitType":1,"iconIndex":76,"message1":" támadás!","message2":"","mpCost":0,"name":"Attack","note":"","occasion":1,"repeats":1,"requiredWtypeId1":0,"requiredWtypeId2":0,"scope":1,"speed":0,"stypeId":0,"successRate":100,"tpCost":0,"tpGain":8},
{"id":2,"animationId":0,"damage":{"critical":false,"elementId":0,"formula":"0","type":0,"variance":20},"description":"","effects":[{"code":21,"dataId":2,"value1":1,"value2":0}],"hitType":0,"iconIndex":81,"message1":" védekezés","message2":"","mpCost":0,"name":"Defence","note":"","occasion":1,"repeats":1,"requiredWtypeId1":0,"requiredWtypeId2":0,"scope":11,"speed":2000,"stypeId":0,"successRate":100,"tpCost":0,"tpGain":13},
{"id":3,"animationId":6,"damage":{"critical":true,"elementId":-1,"formula":"a.atk * (3 + a.level/4) - b.def * 2","type":1,"variance":20},"description":"","effects":[{"code":21,"dataId":0,"value1":1,"value2":0}],"hitType":1,"iconIndex":76,"message1":" támadás!","message2":"","mpCost":0,"name":"Double Attack","note":"","occasion":1,"repeats":2,"requiredWtypeId1":0,"requiredWtypeId2":0,"scope":1,"speed":0,"stypeId":2,"successRate":100,"tpCost":20,"tpGain":0},
{"id":4,"animationId":6,"damage":{"critical":true,"elementId":-1,"formula":"a.atk * ((5/2) + a.level/4) - b.def * 2","type":1,"variance":20},"description":"","effects":[{"code":21,"dataId":0,"value1":1,"value2":0}],"hitType":1,"iconIndex":76,"message1":" támadás!","message2":"","mpCost":0,"name":"Triple Attack","note":"","occasion":1,"repeats":3,"requiredWtypeId1":0,"requiredWtypeId2":0,"scope":1,"speed":0,"stypeId":2,"successRate":100,"tpCost":20,"tpGain":0},
{"id":5,"animationId":6,"damage":{"critical":true,"elementId":-1,"formula":"a.atk * ((2 + a.level/4) - b.def * 2","type":1,"variance":20},"description":"","effects":[{"code":21,"dataId":0,"value1":1,"value2":0}],"hitType":1,"iconIndex":76,"message1":" támadás!","message2":"","mpCost":0,"name":"Fourth Attack","note":"","occasion":1,"repeats":4,"requiredWtypeId1":0,"requiredWtypeId2":0,"scope":1,"speed":0,"stypeId":2,"successRate":100,"tpCost":35,"tpGain":0},
{"id":6,"animationId":23,"damage":{"critical":true,"elementId":1,"formula":"a.atk * (8 + a.level/4) - b.def * 2","type":1,"variance":40},"description":"","effects":[],"hitType":0,"iconIndex":76,"message1":"","message2":"","mpCost":0,"name":"Sword Dance","note":"","occasion":1,"repeats":1,"requiredWtypeId1":0,"requiredWtypeId2":0,"scope":0,"speed":0,"stypeId":2,"successRate":100,"tpCost":20,"tpGain":10},
{"id":7,"animationId":76,"damage":{"critical":true,"elementId":4,"formula":"100 + a.mat * 6 - b.mdf * 2","type":1,"variance":20},"description":"","effects":[{"code":21,"dataId":7,"value1":0.4,"value2":0}],"hitType":2,"iconIndex":66,"message1":" lő %1!","message2":"","mpCost":20,"name":"Lightning","note":"","occasion":1,"repeats":1,"requiredWtypeId1":0,"requiredWtypeId2":0,"scope":2,"speed":0,"stypeId":1,"successRate":100,"tpCost":0,"tpGain":10},
{"id":8,"animationId":66,"damage":{"critical":true,"elementId":2,"formula":"100 + a.mat * (6 + a.level/4) - b.mdf * 2","type":1,"variance":20},"description":"","effects":[{"code":21,"dataId":8,"value1":0.5,"value2":0}],"hitType":2,"iconIndex":64,"message1":" lő %1!","message2":"","mpCost":15,"name":"Fire Blast","note":"","occasion":1,"repeats":1,"requiredWtypeId1":0,"requiredWtypeId2":0,"scope":1,"speed":0,"stypeId":1,"successRate":100,"tpCost":0,"tpGain":10},
{"id":9,"animationId":81,"damage":{"critical":true,"elementId":5,"formula":"100 + a.mat * (8 + a.level/4) - b.mdf * 2","type":1,"variance":20},"description":"","effects":[{"code":21,"dataId":9,"value1":0.8,"value2":0}],"hitType":2,"iconIndex":67,"message1":"","message2":"","mpCost":25,"name":"Water Nebula","note":"","occasion":1,"repeats":1,"requiredWtypeId1":0,"requiredWtypeId2":0,"scope":1,"speed":0,"stypeId":1,"successRate":100,"tpCost":0,"tpGain":0},
{"id":10,"animationId":92,"damage":{"critical":true,"elementId":7,"formula":"100 + a.mat * (10 + a.level/4) - b.mdf * 2","type":1,"variance":30},"description":"","effects":[],"hitType":2,"iconIndex":69,"message1":"","message2":"","mpCost":30,"name":"Tempest","note":"","occasion":0,"repeats":1,"requiredWtypeId1":0,"requiredWtypeId2":0,"scope":1,"speed":0,"stypeId":1,"successRate":100,"tpCost":0,"tpGain":0},
{"id":11,"animationId":102,"damage":{"critical":true,"elementId":9,"formula":"100 + a.mat * (12 + a.level/4) - b.mdf * 2","type":1,"variance":60},"description":"","effects":[{"code":21,"dataId":16,"value1":0.5,"value2":0},{"code":44,"dataId":2,"value1":1,"value2":0},{"code":21,"dataId":4,"value1":0.5,"value2":0}],"hitType":1,"iconIndex":71,"message1":"","message2":"","mpCost":30,"name":"Curse","note":"","occasion":0,"repeats":1,"requiredWtypeId1":0,"requiredWtypeId2":0,"scope":1,"speed":0,"stypeId":1,"successRate":100,"tpCost":0,"tpGain":0},
{"id":12,"animationId":100,"damage":{"critical":false,"elementId":8,"formula":"100 + a.mat * (14 + a.level/4) - b.mdf * 2","type":1,"variance":65},"description":"","effects":[],"hitType":2,"iconIndex":70,"message1":"","message2":"","mpCost":50,"name":"Shining Javelin","note":"","occasion":0,"repeats":1,"requiredWtypeId1":0,"requiredWtypeId2":0,"scope":2,"speed":0,"stypeId":1,"successRate":100,"tpCost":0,"tpGain":0},
{"id":13,"animationId":100,"damage":{"critical":false,"elementId":8,"formula":"100 + a.mat * 25 - b.mdf","type":1,"variance":65},"description":"Hikari Yume !","effects":[],"hitType":2,"iconIndex":70,"message1":"","message2":"","mpCost":200,"name":"Hikari Yume","note":"","occasion":0,"repeats":1,"requiredWtypeId1":0,"requiredWtypeId2":0,"scope":2,"speed":0,"stypeId":1,"successRate":100,"tpCost":0,"tpGain":0},
{"id":14,"animationId":111,"damage":{"critical":true,"elementId":-1,"formula":"a.atk * (4 + a.level/4) - b.def * 2","type":1,"variance":20},"description":"","effects":[{"code":21,"dataId":0,"value1":1,"value2":0}],"hitType":2,"iconIndex":78,"message1":" Támadás!","message2":"","mpCost":2,"name":"Lövés","note":"","occasion":1,"repeats":1,"requiredWtypeId1":0,"requiredWtypeId2":0,"scope":1,"speed":0,"stypeId":1,"successRate":100,"tpCost":0,"tpGain":2},
{"id":15,"animationId":111,"damage":{"critical":true,"elementId":-1,"formula":"a.atk * (4 + a.level/4) - b.def * 2","type":1,"variance":20},"description":"","effects":[{"code":21,"dataId":0,"value1":1,"value2":0}],"hitType":1,"iconIndex":78,"message1":"","message2":"","mpCost":4,"name":"Dupla lövés","note":"","occasion":0,"repeats":2,"requiredWtypeId1":0,"requiredWtypeId2":0,"scope":1,"speed":0,"stypeId":1,"successRate":100,"tpCost":0,"tpGain":5},
{"id":16,"animationId":111,"damage":{"critical":true,"elementId":-1,"formula":"a.atk * (4 + a.level/4) - b.def * 2","type":1,"variance":20},"description":"","effects":[{"code":21,"dataId":0,"value1":1,"value2":0}],"hitType":1,"iconIndex":78,"message1":"","message2":"","mpCost":8,"name":"Tripla lövés","note":"Motion Action: 5\nOugi Animation: _Ougi\nCollapse Effect: 1","occasion":0,"repeats":3,"requiredWtypeId1":0,"requiredWtypeId2":0,"scope":1,"speed":0,"stypeId":1,"successRate":100,"tpCost":0,"tpGain":10},
{"id":17,"animationId":112,"damage":{"critical":true,"elementId":-1,"formula":"a.atk * (10 + a.level/4) - b.def * 2","type":1,"variance":50},"description":"","effects":[{"code":21,"dataId":0,"value1":1,"value2":0}],"hitType":1,"iconIndex":78,"message1":"","message2":"","mpCost":10,"name":"Sorozat lövés","note":"","occasion":0,"repeats":1,"requiredWtypeId1":0,"requiredWtypeId2":0,"scope":1,"speed":0,"stypeId":1,"successRate":100,"tpCost":0,"tpGain":10},
{"id":18,"animationId":8,"damage":{"critical":true,"elementId":2,"formula":"100 + a.mat * (5 + a.level/4) - b.mdf * 2","type":1,"variance":20},"description":"","effects":[{"code":21,"dataId":8,"value1":0.2,"value2":0}],"hitType":1,"iconIndex":76,"message1":"","message2":"","mpCost":10,"name":"Fire Slash","note":"","occasion":0,"repeats":1,"requiredWtypeId1":2,"requiredWtypeId2":0,"scope":1,"speed":0,"stypeId":1,"successRate":100,"tpCost":0,"tpGain":0},
{"id":19,"animationId":9,"damage":{"critical":false,"elementId":3,"formula":"100 + a.mat * (5 + a.level/4) - b.mdf * 2","type":1,"variance":20},"description":"","effects":[{"code":21,"dataId":10,"value1":0.2,"value2":0}],"hitType":1,"iconIndex":76,"message1":"","message2":"","mpCost":10,"name":"Ice Slash","note":"","occasion":0,"repeats":1,"requiredWtypeId1":2,"requiredWtypeId2":0,"scope":1,"speed":0,"stypeId":1,"successRate":100,"tpCost":0,"tpGain":0},
{"id":20,"animationId":51,"damage":{"critical":false,"elementId":0,"formula":"0","type":0,"variance":20},"description":"","effects":[{"code":31,"dataId":2,"value1":5,"value2":0},{"code":31,"dataId":4,"value1":5,"value2":0}],"hitType":0,"iconIndex":34,"message1":"","message2":"","mpCost":15,"name":"Attack Boost","note":"","occasion":0,"repeats":1,"requiredWtypeId1":0,"requiredWtypeId2":0,"scope":11,"speed":0,"stypeId":1,"successRate":100,"tpCost":0,"tpGain":0},
{"id":21,"animationId":41,"damage":{"critical":false,"elementId":0,"formula":"0","type":0,"variance":20},"description":"","effects":[{"code":31,"dataId":0,"value1":5,"value2":0}],"hitType":0,"iconIndex":32,"message1":"","message2":"","mpCost":15,"name":"HP Boost","note":"","occasion":0,"repeats":1,"requiredWtypeId1":0,"requiredWtypeId2":0,"scope":11,"speed":0,"stypeId":1,"successRate":100,"tpCost":0,"tpGain":0},
{"id":22,"animationId":51,"damage":{"critical":false,"elementId":0,"formula":"0","type":0,"variance":20},"description":"","effects":[{"code":13,"dataId":0,"value1":30,"value2":0}],"hitType":0,"iconIndex":82,"message1":"","message2":"","mpCost":15,"name":"Stamina","note":"","occasion":0,"repeats":1,"requiredWtypeId1":0,"requiredWtypeId2":0,"scope":11,"speed":0,"stypeId":1,"successRate":100,"tpCost":0,"tpGain":0},
{"id":23,"animationId":0,"damage":{"critical":false,"elementId":1,"formula":"a.atk * 1","type":1,"variance":20},"description":"","effects":[{"code":32,"dataId":3,"value1":5,"value2":0},{"code":32,"dataId":5,"value1":5,"value2":0}],"hitType":1,"iconIndex":51,"message1":"","message2":"","mpCost":0,"name":"Armor Break","note":"","occasion":0,"repeats":1,"requiredWtypeId1":0,"requiredWtypeId2":0,"scope":1,"speed":0,"stypeId":2,"successRate":100,"tpCost":15,"tpGain":0},
{"id":24,"animationId":52,"damage":{"critical":false,"elementId":0,"formula":"0","type":0,"variance":20},"description":"","effects":[{"code":21,"dataId":14,"value1":1,"value2":0}],"hitType":0,"iconIndex":72,"message1":"","message2":"","mpCost":100,"name":"God General","note":"","occasion":1,"repeats":1,"requiredWtypeId1":0,"requiredWtypeId2":0,"scope":11,"speed":0,"stypeId":1,"successRate":100,"tpCost":0,"tpGain":0},
{"id":25,"animationId":0,"damage":{"critical":false,"elementId":0,"formula":"0","type":0,"variance":20},"description":"","effects":[{"code":21,"dataId":13,"value1":1,"value2":0}],"hitType":0,"iconIndex":67,"message1":"","message2":"","mpCost":5,"name":"Princess Of The Lake","note":"","occasion":1,"repeats":1,"requiredWtypeId1":0,"requiredWtypeId2":0,"scope":1,"speed":0,"stypeId":2,"successRate":100,"tpCost":10,"tpGain":0},
{"id":26,"animationId":0,"damage":{"critical":false,"elementId":0,"formula":"0","type":0,"variance":20},"description":"Heal your teammate","effects":[{"code":11,"dataId":0,"value1":0.3,"value2":0}],"hitType":0,"iconIndex":84,"message1":"","message2":"","mpCost":20,"name":"Healing","note":"Védd meg a falut II.","occasion":1,"repeats":1,"requiredWtypeId1":0,"requiredWtypeId2":0,"scope":7,"speed":0,"stypeId":1,"successRate":100,"tpCost":0,"tpGain":0},
{"id":27,"animationId":0,"damage":{"critical":false,"elementId":0,"formula":"0","type":0,"variance":20},"description":"","effects":[],"hitType":0,"iconIndex":0,"message1":"","message2":"","mpCost":0,"name":"","note":"","occasion":0,"repeats":1,"requiredWtypeId1":0,"requiredWtypeId2":0,"scope":1,"speed":0,"stypeId":1,"successRate":100,"tpCost":0,"tpGain":0},
{"id":28,"animationId":16,"damage":{"critical":true,"elementId":-1,"formula":"a.atk * 6 - b.def * 2","type":1,"variance":50},"description":"","effects":[{"code":21,"dataId":0,"value1":1,"value2":0}],"hitType":1,"iconIndex":78,"message1":" támadás!","message2":"","mpCost":0,"name":"Claws","note":"Vérfarkasok","occasion":1,"repeats":1,"requiredWtypeId1":0,"requiredWtypeId2":0,"scope":1,"speed":0,"stypeId":0,"successRate":100,"tpCost":0,"tpGain":10},
{"id":29,"animationId":28,"damage":{"critical":true,"elementId":0,"formula":"a.atk * 8 - b.def * 2","type":1,"variance":20},"description":"","effects":[{"code":21,"dataId":3,"value1":0.5,"value2":0}],"hitType":1,"iconIndex":5,"message1":"","message2":"","mpCost":0,"name":"Posion","note":"Méreggel rendelkező szörnyek","occasion":0,"repeats":1,"requiredWtypeId1":0,"requiredWtypeId2":0,"scope":1,"speed":0,"stypeId":2,"successRate":100,"tpCost":0,"tpGain":0},
{"id":30,"animationId":2,"damage":{"critical":false,"elementId":0,"formula":"a.atk * 7 - b.def * 2","type":1,"variance":20},"description":"","effects":[],"hitType":0,"iconIndex":110,"message1":"","message2":"","mpCost":0,"name":"Ogre","note":"Ogre képesség","occasion":0,"repeats":1,"requiredWtypeId1":0,"requiredWtypeId2":0,"scope":1,"speed":0,"stypeId":2,"successRate":100,"tpCost":0,"tpGain":0},
{"id":31,"animationId":27,"damage":{"critical":true,"elementId":9,"formula":"a.atk * 10 - b.def * 2","type":1,"variance":50},"description":"","effects":[],"hitType":1,"iconIndex":76,"message1":"","message2":"","mpCost":0,"name":"Slash Storm","note":"","occasion":0,"repeats":1,"requiredWtypeId1":0,"requiredWtypeId2":0,"scope":1,"speed":0,"stypeId":2,"successRate":100,"tpCost":20,"tpGain":0},
{"id":32,"animationId":28,"damage":{"critical":true,"elementId":-1,"formula":"a.atk * 8 - b.def * 2","type":1,"variance":50},"description":"","effects":[{"code":21,"dataId":0,"value1":1,"value2":0},{"code":21,"dataId":4,"value1":0.3,"value2":0}],"hitType":1,"iconIndex":78,"message1":" támadás!","message2":"","mpCost":20,"name":"Blood Claws","note":"Vérfarkasok","occasion":1,"repeats":1,"requiredWtypeId1":0,"requiredWtypeId2":0,"scope":1,"speed":0,"stypeId":0,"successRate":100,"tpCost":0,"tpGain":10},
{"id":33,"animationId":102,"damage":{"critical":true,"elementId":9,"formula":"a.atk * 9 - b.def * 2","type":1,"variance":20},"description":"","effects":[],"hitType":0,"iconIndex":71,"message1":"","message2":"","mpCost":20,"name":"Dark Bullet","note":"","occasion":0,"repeats":1,"requiredWtypeId1":0,"requiredWtypeId2":0,"scope":1,"speed":0,"stypeId":1,"successRate":100,"tpCost":0,"tpGain":0},
{"id":34,"animationId":64,"damage":{"critical":false,"elementId":0,"formula":"a.atk * 2 - b.def * 2","type":1,"variance":20},"description":"","effects":[{"code":21,"dataId":7,"value1":1,"value2":0}],"hitType":0,"iconIndex":5,"message1":"","message2":"","mpCost":0,"name":"Vampire Paralyze","note":"","occasion":0,"repeats":1,"requiredWtypeId1":0,"requiredWtypeId2":0,"scope":1,"speed":0,"stypeId":1,"successRate":100,"tpCost":0,"tpGain":0},
{"id":35,"animationId":-1,"damage":{"critical":true,"elementId":-1,"formula":"a.atk * 4 - b.def * 2","type":1,"variance":20},"description":"","effects":[{"code":21,"dataId":0,"value1":1,"value2":0}],"hitType":1,"iconIndex":76,"message1":" támadás!","message2":"","mpCost":0,"name":"EAttack","note":"Enemy Attack","occasion":1,"repeats":1,"requiredWtypeId1":0,"requiredWtypeId2":0,"scope":1,"speed":0,"stypeId":0,"successRate":100,"tpCost":0,"tpGain":8},
{"id":36,"animationId":6,"damage":{"critical":true,"elementId":-1,"formula":"a.atk * 3 - b.def * 2","type":1,"variance":20},"description":"","effects":[{"code":21,"dataId":0,"value1":1,"value2":0}],"hitType":1,"iconIndex":76,"message1":" támadás!","message2":"","mpCost":0,"name":"EDouble Attack","note":"","occasion":1,"repeats":2,"requiredWtypeId1":0,"requiredWtypeId2":0,"scope":1,"speed":0,"stypeId":2,"successRate":100,"tpCost":20,"tpGain":0},
{"id":37,"animationId":0,"damage":{"critical":false,"elementId":0,"formula":"0","type":0,"variance":20},"description":"","effects":[],"hitType":0,"iconIndex":0,"message1":"","message2":"","mpCost":0,"name":"","note":"","occasion":0,"repeats":1,"requiredWtypeId1":0,"requiredWtypeId2":0,"scope":1,"speed":0,"stypeId":1,"successRate":100,"tpCost":0,"tpGain":0},
{"id":38,"animationId":0,"damage":{"critical":false,"elementId":0,"formula":"0","type":0,"variance":20},"description":"","effects":[],"hitType":0,"iconIndex":0,"message1":"","message2":"","mpCost":0,"name":"","note":"","occasion":0,"repeats":1,"requiredWtypeId1":0,"requiredWtypeId2":0,"scope":1,"speed":0,"stypeId":1,"successRate":100,"tpCost":0,"tpGain":0},
{"id":39,"animationId":0,"damage":{"critical":false,"elementId":0,"formula":"0","type":0,"variance":20},"description":"","effects":[],"hitType":0,"iconIndex":0,"message1":"","message2":"","mpCost":0,"name":"","note":"","occasion":0,"repeats":1,"requiredWtypeId1":0,"requiredWtypeId2":0,"scope":1,"speed":0,"stypeId":1,"successRate":100,"tpCost":0,"tpGain":0},
{"id":40,"animationId":0,"damage":{"critical":false,"elementId":0,"formula":"0","type":0,"variance":20},"description":"","effects":[],"hitType":0,"iconIndex":0,"message1":"","message2":"","mpCost":0,"name":"","note":"","occasion":0,"repeats":1,"requiredWtypeId1":0,"requiredWtypeId2":0,"scope":1,"speed":0,"stypeId":1,"successRate":100,"tpCost":0,"tpGain":0},
{"id":41,"animationId":0,"damage":{"critical":false,"elementId":0,"formula":"0","type":0,"variance":20},"description":"","effects":[],"hitType":0,"iconIndex":0,"message1":"","message2":"","mpCost":0,"name":"","note":"","occasion":0,"repeats":1,"requiredWtypeId1":0,"requiredWtypeId2":0,"scope":1,"speed":0,"stypeId":1,"successRate":100,"tpCost":0,"tpGain":0},
{"id":42,"animationId":0,"damage":{"critical":false,"elementId":0,"formula":"0","type":0,"variance":20},"description":"","effects":[],"hitType":0,"iconIndex":0,"message1":"","message2":"","mpCost":0,"name":"","note":"","occasion":0,"repeats":1,"requiredWtypeId1":0,"requiredWtypeId2":0,"scope":1,"speed":0,"stypeId":1,"successRate":100,"tpCost":0,"tpGain":0},
{"id":43,"animationId":0,"damage":{"critical":false,"elementId":0,"formula":"0","type":0,"variance":20},"description":"","effects":[],"hitType":0,"iconIndex":0,"message1":"","message2":"","mpCost":0,"name":"","note":"","occasion":0,"repeats":1,"requiredWtypeId1":0,"requiredWtypeId2":0,"scope":1,"speed":0,"stypeId":1,"successRate":100,"tpCost":0,"tpGain":0},
{"id":44,"animationId":0,"damage":{"critical":false,"elementId":0,"formula":"0","type":0,"variance":20},"description":"","effects":[],"hitType":0,"iconIndex":0,"message1":"","message2":"","mpCost":0,"name":"","note":"","occasion":0,"repeats":1,"requiredWtypeId1":0,"requiredWtypeId2":0,"scope":1,"speed":0,"stypeId":1,"successRate":100,"tpCost":0,"tpGain":0},
{"id":45,"animationId":0,"damage":{"critical":false,"elementId":0,"formula":"0","type":0,"variance":20},"description":"","effects":[],"hitType":0,"iconIndex":0,"message1":"","message2":"","mpCost":0,"name":"","note":"","occasion":0,"repeats":1,"requiredWtypeId1":0,"requiredWtypeId2":0,"scope":1,"speed":0,"stypeId":1,"successRate":100,"tpCost":0,"tpGain":0},
{"id":46,"animationId":0,"damage":{"critical":false,"elementId":0,"formula":"0","type":0,"variance":20},"description":"","effects":[],"hitType":0,"iconIndex":0,"message1":"","message2":"","mpCost":0,"name":"","note":"","occasion":0,"repeats":1,"requiredWtypeId1":0,"requiredWtypeId2":0,"scope":1,"speed":0,"stypeId":1,"successRate":100,"tpCost":0,"tpGain":0},
{"id":47,"animationId":0,"damage":{"critical":false,"elementId":0,"formula":"0","type":0,"variance":20},"description":"","effects":[],"hitType":0,"iconIndex":0,"message1":"","message2":"","mpCost":0,"name":"","note":"","occasion":0,"repeats":1,"requiredWtypeId1":0,"requiredWtypeId2":0,"scope":1,"speed":0,"stypeId":1,"successRate":100,"tpCost":0,"tpGain":0},
{"id":48,"animationId":0,"damage":{"critical":false,"elementId":0,"formula":"0","type":0,"variance":20},"description":"","effects":[],"hitType":0,"iconIndex":0,"message1":"","message2":"","mpCost":0,"name":"","note":"","occasion":0,"repeats":1,"requiredWtypeId1":0,"requiredWtypeId2":0,"scope":1,"speed":0,"stypeId":1,"successRate":100,"tpCost":0,"tpGain":0},
{"id":49,"animationId":0,"damage":{"critical":false,"elementId":0,"formula":"0","type":0,"variance":20},"description":"","effects":[],"hitType":0,"iconIndex":0,"message1":"","message2":"","mpCost":0,"name":"","note":"","occasion":0,"repeats":1,"requiredWtypeId1":0,"requiredWtypeId2":0,"scope":1,"speed":0,"stypeId":1,"successRate":100,"tpCost":0,"tpGain":0},
{"id":50,"animationId":0,"damage":{"critical":false,"elementId":0,"formula":"0","type":0,"variance":20},"description":"","effects":[],"hitType":0,"iconIndex":0,"message1":"","message2":"","mpCost":0,"name":"","note":"","occasion":0,"repeats":1,"requiredWtypeId1":0,"requiredWtypeId2":0,"scope":1,"speed":0,"stypeId":1,"successRate":100,"tpCost":0,"tpGain":0},
{"id":51,"animationId":0,"damage":{"critical":false,"elementId":0,"formula":"0","type":0,"variance":20},"description":"","effects":[],"hitType":0,"iconIndex":0,"message1":"","message2":"","mpCost":0,"name":"","note":"","occasion":0,"repeats":1,"requiredWtypeId1":0,"requiredWtypeId2":0,"scope":1,"speed":0,"stypeId":1,"successRate":100,"tpCost":0,"tpGain":0},
{"id":52,"animationId":0,"damage":{"critical":false,"elementId":0,"formula":"0","type":0,"variance":20},"description":"","effects":[],"hitType":0,"iconIndex":0,"message1":"","message2":"","mpCost":0,"name":"","note":"","occasion":0,"repeats":1,"requiredWtypeId1":0,"requiredWtypeId2":0,"scope":1,"speed":0,"stypeId":1,"successRate":100,"tpCost":0,"tpGain":0},
{"id":53,"animationId":0,"damage":{"critical":false,"elementId":0,"formula":"0","type":0,"variance":20},"description":"","effects":[],"hitType":0,"iconIndex":0,"message1":"","message2":"","mpCost":0,"name":"","note":"","occasion":0,"repeats":1,"requiredWtypeId1":0,"requiredWtypeId2":0,"scope":1,"speed":0,"stypeId":1,"successRate":100,"tpCost":0,"tpGain":0},
{"id":54,"animationId":0,"damage":{"critical":false,"elementId":0,"formula":"0","type":0,"variance":20},"description":"","effects":[],"hitType":0,"iconIndex":0,"message1":"","message2":"","mpCost":0,"name":"","note":"","occasion":0,"repeats":1,"requiredWtypeId1":0,"requiredWtypeId2":0,"scope":1,"speed":0,"stypeId":1,"successRate":100,"tpCost":0,"tpGain":0},
{"id":55,"animationId":76,"damage":{"critical":true,"elementId":4,"formula":"100 + a.mat * 12 - b.mdf * 2","type":1,"variance":20},"description":"","effects":[{"code":21,"dataId":7,"value1":0.5,"value2":0},{"code":44,"dataId":3,"value1":1,"value2":0}],"hitType":2,"iconIndex":66,"message1":" lő %1!","message2":"","mpCost":20,"name":"Chain Lightning","note":"<ReplaceSkill: 7>","occasion":1,"repeats":1,"requiredWtypeId1":0,"requiredWtypeId2":0,"scope":1,"speed":0,"stypeId":1,"successRate":100,"tpCost":0,"tpGain":10}
]