[
null,
{"id":1,"animationId":6,"description":"Often used this Sword during trainings, made from wood.","etypeId":1,"traits":[{"code":31,"dataId":1,"value":0},{"code":22,"dataId":0,"value":0}],"iconIndex":97,"name":"Training Sword","note":"Class E","params":[0,0,10,0,10,0,0,0],"price":10,"wtypeId":2},
{"id":2,"animationId":6,"description":"The best blacksmith in the village made this Sword from good quality iron.","etypeId":1,"traits":[{"code":31,"dataId":1,"value":0},{"code":22,"dataId":0,"value":0}],"iconIndex":97,"name":"Iron Sword","note":"Class E+","params":[0,0,20,0,0,0,0,0],"price":30,"wtypeId":2},
{"id":3,"animationId":6,"description":"An essential equipment for novice adventurers.","etypeId":1,"traits":[{"code":31,"dataId":1,"value":0},{"code":22,"dataId":0,"value":0}],"iconIndex":97,"name":"Adventurer Sword","note":"Class D","params":[0,0,25,0,0,0,0,0],"price":60,"wtypeId":2},
{"id":4,"animationId":6,"description":"A rare Sword for only true warriors.","etypeId":1,"traits":[{"code":31,"dataId":1,"value":0},{"code":22,"dataId":0,"value":0}],"iconIndex":97,"name":"Warrior's Sword","note":"Class D+","params":[0,0,35,0,0,0,0,0],"price":90,"wtypeId":2},
{"id":5,"animationId":7,"description":"Warrior's Sword type inside a magic core.","etypeId":1,"traits":[{"code":31,"dataId":1,"value":0},{"code":22,"dataId":0,"value":0}],"iconIndex":97,"name":"Magic Sword","note":"Class C","params":[0,0,35,0,25,0,0,0],"price":120,"wtypeId":2},
{"id":6,"animationId":25,"description":"The Demon Sword which made in the Demon Realm.\nDanger Weapon!","etypeId":1,"traits":[{"code":31,"dataId":1,"value":0},{"code":22,"dataId":0,"value":0},{"code":31,"dataId":9,"value":1},{"code":13,"dataId":15,"value":0.1}],"iconIndex":125,"name":"Darkness","note":"Class C+","params":[0,0,50,0,50,0,0,0],"price":160,"wtypeId":2},
{"id":7,"animationId":0,"description":"","etypeId":1,"traits":[{"code":31,"dataId":1,"value":0},{"code":22,"dataId":0,"value":0}],"iconIndex":101,"name":"Wand","note":"Class D","params":[0,0,0,0,25,0,0,0],"price":0,"wtypeId":13},
{"id":8,"animationId":0,"description":"","etypeId":1,"traits":[{"code":31,"dataId":1,"value":0},{"code":22,"dataId":0,"value":0}],"iconIndex":0,"name":"","note":"","params":[0,0,0,0,0,0,0,0],"price":0,"wtypeId":0},
{"id":9,"animationId":0,"description":"","etypeId":1,"traits":[{"code":31,"dataId":1,"value":0},{"code":22,"dataId":0,"value":0}],"iconIndex":0,"name":"","note":"","params":[0,0,0,0,0,0,0,0],"price":0,"wtypeId":0},
{"id":10,"animationId":0,"description":"","etypeId":1,"traits":[{"code":31,"dataId":1,"value":0},{"code":22,"dataId":0,"value":0}],"iconIndex":0,"name":"","note":"","params":[0,0,0,0,0,0,0,0],"price":0,"wtypeId":0},
{"id":11,"animationId":0,"description":"","etypeId":1,"traits":[{"code":31,"dataId":1,"value":0},{"code":22,"dataId":0,"value":0}],"iconIndex":0,"name":"","note":"","params":[0,0,0,0,0,0,0,0],"price":0,"wtypeId":0},
{"id":12,"animationId":0,"description":"","etypeId":1,"traits":[{"code":31,"dataId":1,"value":0},{"code":22,"dataId":0,"value":0}],"iconIndex":0,"name":"","note":"","params":[0,0,0,0,0,0,0,0],"price":0,"wtypeId":0},
{"id":13,"animationId":0,"description":"","etypeId":1,"traits":[{"code":31,"dataId":1,"value":0},{"code":22,"dataId":0,"value":0}],"iconIndex":0,"name":"","note":"","params":[0,0,0,0,0,0,0,0],"price":0,"wtypeId":0},
{"id":14,"animationId":0,"description":"","etypeId":1,"traits":[{"code":31,"dataId":1,"value":0},{"code":22,"dataId":0,"value":0}],"iconIndex":0,"name":"","note":"","params":[0,0,0,0,0,0,0,0],"price":0,"wtypeId":0}
]